senoquant_stardist_ext.libs/libgomp-a34b3233.so.1.0.0
senoquant_stardist_ext-0.1.0.dist-info/WHEEL
senoquant_stardist_ext-0.1.0.dist-info/METADATA
senoquant_stardist_ext-0.1.0.dist-info/RECORD
senoquant_stardist_ext-0.1.0.dist-info/licenses/LICENSE
senoquant/tabs/segmentation/stardist_onnx_utils/_stardist/lib/stardist2d.so
senoquant/tabs/segmentation/stardist_onnx_utils/_stardist/lib/stardist3d.so
