Metadata-Version: 2.2
Name: senoquant-stardist-ext
Version: 0.1.0
Summary: Prebuilt StarDist C/C++ extensions for SenoQuant
Keywords: napari,stardist,segmentation,image-processing,native-extensions
Author: SenoQuant Team
License: BSD 3-Clause License
Classifier: Development Status :: 4 - Beta
Classifier: Intended Audience :: Science/Research
Classifier: License :: OSI Approved :: BSD License
Classifier: Operating System :: MacOS
Classifier: Operating System :: Microsoft :: Windows
Classifier: Operating System :: POSIX :: Linux
Classifier: Programming Language :: C
Classifier: Programming Language :: C++
Classifier: Programming Language :: Python :: 3
Classifier: Programming Language :: Python :: 3 :: Only
Classifier: Topic :: Scientific/Engineering :: Image Processing
Project-URL: Homepage, https://github.com/HaamsRee/senoquant-dev
Project-URL: Repository, https://github.com/HaamsRee/senoquant-dev
Project-URL: Issues, https://github.com/HaamsRee/senoquant-dev/issues
Requires-Python: >=3.11
